pyWebman/__init__.py
pyWebman/webman.py
pyWebman-0.1.1.dist-info/METADATA
pyWebman-0.1.1.dist-info/WHEEL
pyWebman-0.1.1.dist-info/entry_points.txt
pyWebman-0.1.1.dist-info/top_level.txt
pyWebman-0.1.1.dist-info/RECORD
